{
	"name": "Blue Dream Feminized",
	"url": "https://seedsupreme.com/blue-dream-feminized.html",
	"slug": "blue-dream-feminized",
	"imageUrl": "https://seedsupreme.com/media/catalog/product/cache/b88350ab5fb747a1264cdcee4ae58d08/a/k/ak-47_3.png",
	"basePrice": "$44.00",
	"basePriceNum": 44,
	"packOptions": [
		{
			"packSize": 4,
			"totalPrice": 44,
			"originalPrice": 55,
			"pricePerSeed": 11,
			"discount": 20
		},
		{
			"packSize": 8,
			"totalPrice": 69.6,
			"originalPrice": 87,
			"pricePerSeed": 8.7,
			"discount": 20
		},
		{
			"packSize": 12,
			"totalPrice": 87.2,
			"originalPrice": 109,
			"pricePerSeed": 7.266666666666667,
			"discount": 20
		},
		{
			"packSize": 25,
			"totalPrice": 130.4,
			"originalPrice": 163,
			"pricePerSeed": 5.216,
			"discount": 20
		}
	],
	"specs": {
		"variety": "Hybrid",
		"thcContent": "High (15-20%)",
		"floweringPeriod": "8-10 Weeks",
		"floweringType": "Photoperiod",
		"cbdContent": "Low (0-1%)"
	},
	"variety": "Hybrid",
	"thcLevel": "High (15-20%)",
	"scrapedAt": "2025-11-29T17:49:37.336Z"
}