{
	"id": "BXHT9lEhNFjUNOw",
	"json": "{\"id\":\"BXHT9lEhNFjUNOw\",\"url\":\"https://seedsupreme.com/big-bud-autoflower.html\",\"loadedUrl\":\"https://seedsupreme.com/big-bud-autoflower.html\",\"uniqueKey\":\"https://seedsupreme.com/big-bud-autoflower.html\",\"method\":\"GET\",\"noRetry\":false,\"retryCount\":0,\"errorMessages\":[],\"headers\":{},\"userData\":{\"__crawlee\":{\"state\":4}},\"handledAt\":\"2025-11-29T05:04:47.893Z\"}",
	"method": "GET",
	"orderNo": null,
	"retryCount": 0,
	"uniqueKey": "https://seedsupreme.com/big-bud-autoflower.html",
	"url": "https://seedsupreme.com/big-bud-autoflower.html"
}